{
  "title": "Pool Cleaning Best Practices for Arizona Homeowners",
  "excerpt": "Arizona's extreme summer heat poses unique challenges for pool maintenance. Learn essential tips to keep your pool pristine during the hottest months of the year, from managing evaporation to balancing chemicals in high temperatures.",
  "author": {
    "name": "All-Star Pools",
    "bio": "Our team of certified pool technicians has over 20 years of experience maintaining pools across the Phoenix Valley."
  },
  "publishedAt": "2024-06-10T10:00:00Z",
  "tags": ["summer maintenance", "Arizona pools", "water chemistry", "pool care tips", "desert climate"],
  "image": "https://images.unsplash.com/photo-1575429198097-0414ec08e8cd?ixlib=rb-4.0.3&auto=format&fit=crop&w=1200&q=80",
  "imageAlt": "Infinity edge swimming pool",
  "featured": true,
  "content": "<article class='prose prose-lg max-w-none'><h2>Why Arizona Summer Pool Maintenance is Different</h2><p>Arizona summers are unlike anywhere else in the country. With temperatures regularly exceeding 110°F and intense UV radiation, your swimming pool faces unique challenges that require specialized maintenance approaches. Understanding these challenges is the first step to maintaining a beautiful, safe pool all summer long.</p><h2>The Arizona Summer Pool Challenge: Key Issues</h2><h3>1. Rapid Water Evaporation</h3><p>During Phoenix's hottest months, pools can lose up to 2 inches of water per week through evaporation. This isn't just a water bill issue – as water evaporates, it leaves behind minerals and chemicals, concentrating them in your remaining water and throwing off your carefully balanced chemistry.</p><h3>2. Increased Chemical Consumption</h3><p>Arizona's intense UV rays break down chlorine faster than in other climates. The sun's radiation can destroy up to 90% of your pool's chlorine in just a few hours on the hottest days. This means you'll need to add chlorine more frequently and possibly switch to stabilized chlorine products.</p><h3>3. Algae Growth Acceleration</h3><p>Warm water is a perfect breeding ground for algae. When your pool water temperature exceeds 85°F (which happens quickly in Arizona), algae can bloom almost overnight if your sanitizer levels drop even slightly.</p><h2>Essential Summer Pool Maintenance Tasks</h2><h3>Daily Maintenance (5-10 minutes)</h3><ul><li><strong>Check and adjust water level:</strong> Keep water at the middle of your skimmer opening. Add water as needed to compensate for evaporation.</li><li><strong>Skim debris:</strong> Remove leaves, insects, and other floating debris before they sink and become harder to remove.</li><li><strong>Empty skimmer baskets:</strong> Clogged baskets reduce circulation and filtration efficiency.</li><li><strong>Check pool equipment:</strong> Ensure your pump is running smoothly and there are no leaks.</li></ul><h3>Weekly Maintenance (30-45 minutes)</h3><ul><li><strong>Test water chemistry:</strong> Use a quality test kit to check pH (7.2-7.6), total alkalinity (80-120 ppm), and chlorine levels (3-5 ppm for summer).</li><li><strong>Brush walls and floor:</strong> Even if your pool looks clean, brushing prevents algae from getting established.</li><li><strong>Vacuum the pool:</strong> Remove settled debris and dirt from the pool floor.</li><li><strong>Clean the filter:</strong> Backwash or clean your filter according to manufacturer guidelines.</li><li><strong>Shock the pool:</strong> Add shock treatment in the evening to boost chlorine levels overnight.</li></ul><h2>Arizona-Specific Tips for Summer Success</h2><h3>Increase Your Chlorine Stabilizer</h3><p>Cyanuric acid (CYA) protects chlorine from UV degradation. In Arizona, maintain CYA levels between 50-80 ppm (higher than the typical 30-50 ppm recommended elsewhere). However, don't exceed 100 ppm, as this can make your chlorine less effective.</p><h3>Run Your Pump Longer</h3><p>During peak summer, run your pool pump 10-12 hours per day instead of the typical 8 hours. This ensures adequate circulation and filtration. Consider running it during off-peak electricity hours to save on energy costs.</p><h3>Consider a Pool Cover</h3><p>While not always practical for daily use, a pool cover can reduce evaporation by up to 95%. Even using a cover overnight or when you're away can make a significant difference in water and chemical conservation.</p><h3>Monitor Calcium Hardness</h3><p>Arizona has notoriously hard water. Test calcium hardness monthly and maintain levels between 200-400 ppm. High calcium can cause scaling, while low calcium can damage pool surfaces.</p><h2>Chemical Balance in Extreme Heat</h2><p>Maintaining proper water chemistry is more critical – and more challenging – during Arizona summers:</p><ul><li><strong>pH:</strong> Heat tends to raise pH. Check and adjust 2-3 times per week.</li><li><strong>Chlorine:</strong> Test daily during peak summer. Consider switching to trichlor tablets or liquid chlorine for better UV stability.</li><li><strong>Phosphates:</strong> Control phosphate levels (below 100 ppb) to prevent algae growth in warm water.</li><li><strong>Total Dissolved Solids (TDS):</strong> High evaporation rates increase TDS. If levels exceed 2,500 ppm, consider partial water replacement.</li></ul><h2>When to Call a Professional</h2><p>While regular maintenance can be DIY, certain situations warrant professional help:</p><ul><li>Green pool or severe algae outbreak</li><li>Equipment malfunction or unusual noises</li><li>Persistent chemistry problems despite regular treatment</li><li>Staining or surface damage</li><li>Converting to salt water or other system upgrades</li></ul><h2>Conclusion: Consistency is Key</h2><p>Arizona summer pool maintenance requires diligence, but with a consistent routine, you can enjoy crystal-clear water all season long. The key is staying ahead of problems rather than reacting to them. A little daily attention prevents major issues and keeps your pool as the refreshing oasis it should be during our scorching summers.</p><p>Remember, when in doubt, it's always better to test your water and make small adjustments frequently rather than waiting for visible problems to develop. Your pool – and everyone who swims in it – will thank you for the extra care.</p></article>",
  "seo": {
    "title": "Arizona Summer Pool Maintenance Guide 2024 | Expert Tips",
    "description": "Complete guide to maintaining your Arizona pool during extreme summer heat. Learn about evaporation control, chemical balance, and UV protection for crystal-clear water.",
    "keywords": ["Arizona pool maintenance", "summer pool care", "Phoenix pool service", "pool evaporation", "desert pool maintenance", "pool chemical balance"]
  }
}
